[
    {
        "url": "http:\/\/localhost:8080",
        "last_updated": "2025-05-13T22:14:41+00:00",
        "data": {
            "meta": {
                "generated_at": "2025-05-13T22:14:40+00:00",
                "source": "http:\/\/localhost:8080"
            },
            "taxonomies": {
                "category": {
                    "info": {
                        "name": "Categories",
                        "slug": "category",
                        "description": "",
                        "types": [
                            "post"
                        ],
                        "hierarchical": true,
                        "rest_base": "categories",
                        "_links": {
                            "collection": [
                                {
                                    "href": "http:\/\/localhost:8080\/wp-json\/wp\/v2\/taxonomies"
                                }
                            ],
                            "wp:items": [
                                {
                                    "href": "http:\/\/localhost:8080\/wp-json\/wp\/v2\/categories"
                                }
                            ],
                            "curies": [
                                {
                                    "name": "wp",
                                    "href": "https:\/\/api.w.org\/{rel}",
                                    "templated": true
                                }
                            ]
                        }
                    },
                    "terms": []
                },
                "post_tag": {
                    "info": {
                        "name": "Tags",
                        "slug": "post_tag",
                        "description": "",
                        "types": [
                            "post"
                        ],
                        "hierarchical": false,
                        "rest_base": "tags",
                        "_links": {
                            "collection": [
                                {
                                    "href": "http:\/\/localhost:8080\/wp-json\/wp\/v2\/taxonomies"
                                }
                            ],
                            "wp:items": [
                                {
                                    "href": "http:\/\/localhost:8080\/wp-json\/wp\/v2\/tags"
                                }
                            ],
                            "curies": [
                                {
                                    "name": "wp",
                                    "href": "https:\/\/api.w.org\/{rel}",
                                    "templated": true
                                }
                            ]
                        }
                    },
                    "terms": []
                },
                "zona": {
                    "info": {
                        "name": "Zona de Reporte",
                        "slug": "zona",
                        "description": "",
                        "types": [
                            "bitacora",
                            "fosa"
                        ],
                        "hierarchical": true,
                        "rest_base": "zona",
                        "_links": {
                            "collection": [
                                {
                                    "href": "http:\/\/localhost:8080\/wp-json\/wp\/v2\/taxonomies"
                                }
                            ],
                            "wp:items": [
                                {
                                    "href": "http:\/\/localhost:8080\/wp-json\/wp\/v2\/zona"
                                }
                            ],
                            "curies": [
                                {
                                    "name": "wp",
                                    "href": "https:\/\/api.w.org\/{rel}",
                                    "templated": true
                                }
                            ]
                        }
                    },
                    "terms": [
                        {
                            "id": 5,
                            "count": 1,
                            "description": "",
                            "link": "http:\/\/localhost:8080\/zona\/hijo-zona-1\/",
                            "name": "Hijo Zona 1",
                            "slug": "hijo-zona-1",
                            "taxonomy": "zona",
                            "parent": 4,
                            "meta": [],
                            "_links": {
                                "self": [
                                    {
                                        "href": "http:\/\/localhost:8080\/wp-json\/wp\/v2\/zona\/5"
                                    }
                                ],
                                "collection": [
                                    {
                                        "href": "http:\/\/localhost:8080\/wp-json\/wp\/v2\/zona"
                                    }
                                ],
                                "about": [
                                    {
                                        "href": "http:\/\/localhost:8080\/wp-json\/wp\/v2\/taxonomies\/zona"
                                    }
                                ],
                                "up": [
                                    {
                                        "embeddable": true,
                                        "href": "http:\/\/localhost:8080\/wp-json\/wp\/v2\/zona\/4"
                                    }
                                ],
                                "wp:post_type": [
                                    {
                                        "href": "http:\/\/localhost:8080\/wp-json\/wp\/v2\/bitacora?zona=5"
                                    },
                                    {
                                        "href": "http:\/\/localhost:8080\/wp-json\/wp\/v2\/fosa?zona=5"
                                    }
                                ],
                                "curies": [
                                    {
                                        "name": "wp",
                                        "href": "https:\/\/api.w.org\/{rel}",
                                        "templated": true
                                    }
                                ]
                            }
                        },
                        {
                            "id": 4,
                            "count": 1,
                            "description": "",
                            "link": "http:\/\/localhost:8080\/zona\/zona-1\/",
                            "name": "Zona 1",
                            "slug": "zona-1",
                            "taxonomy": "zona",
                            "parent": 0,
                            "meta": [],
                            "_links": {
                                "self": [
                                    {
                                        "href": "http:\/\/localhost:8080\/wp-json\/wp\/v2\/zona\/4"
                                    }
                                ],
                                "collection": [
                                    {
                                        "href": "http:\/\/localhost:8080\/wp-json\/wp\/v2\/zona"
                                    }
                                ],
                                "about": [
                                    {
                                        "href": "http:\/\/localhost:8080\/wp-json\/wp\/v2\/taxonomies\/zona"
                                    }
                                ],
                                "wp:post_type": [
                                    {
                                        "href": "http:\/\/localhost:8080\/wp-json\/wp\/v2\/bitacora?zona=4"
                                    },
                                    {
                                        "href": "http:\/\/localhost:8080\/wp-json\/wp\/v2\/fosa?zona=4"
                                    }
                                ],
                                "curies": [
                                    {
                                        "name": "wp",
                                        "href": "https:\/\/api.w.org\/{rel}",
                                        "templated": true
                                    }
                                ]
                            }
                        },
                        {
                            "id": 3,
                            "count": 2,
                            "description": "",
                            "link": "http:\/\/localhost:8080\/zona\/zona-2\/",
                            "name": "Zona 2",
                            "slug": "zona-2",
                            "taxonomy": "zona",
                            "parent": 0,
                            "meta": [],
                            "_links": {
                                "self": [
                                    {
                                        "href": "http:\/\/localhost:8080\/wp-json\/wp\/v2\/zona\/3"
                                    }
                                ],
                                "collection": [
                                    {
                                        "href": "http:\/\/localhost:8080\/wp-json\/wp\/v2\/zona"
                                    }
                                ],
                                "about": [
                                    {
                                        "href": "http:\/\/localhost:8080\/wp-json\/wp\/v2\/taxonomies\/zona"
                                    }
                                ],
                                "wp:post_type": [
                                    {
                                        "href": "http:\/\/localhost:8080\/wp-json\/wp\/v2\/bitacora?zona=3"
                                    },
                                    {
                                        "href": "http:\/\/localhost:8080\/wp-json\/wp\/v2\/fosa?zona=3"
                                    }
                                ],
                                "curies": [
                                    {
                                        "name": "wp",
                                        "href": "https:\/\/api.w.org\/{rel}",
                                        "templated": true
                                    }
                                ]
                            }
                        }
                    ]
                },
                "tipo_prenda": {
                    "info": {
                        "name": "Tipo de Prenda",
                        "slug": "tipo_prenda",
                        "description": "",
                        "types": [
                            "indicio"
                        ],
                        "hierarchical": false,
                        "rest_base": "tipo_prenda",
                        "_links": {
                            "collection": [
                                {
                                    "href": "http:\/\/localhost:8080\/wp-json\/wp\/v2\/taxonomies"
                                }
                            ],
                            "wp:items": [
                                {
                                    "href": "http:\/\/localhost:8080\/wp-json\/wp\/v2\/tipo_prenda"
                                }
                            ],
                            "curies": [
                                {
                                    "name": "wp",
                                    "href": "https:\/\/api.w.org\/{rel}",
                                    "templated": true
                                }
                            ]
                        }
                    },
                    "terms": [
                        {
                            "id": 6,
                            "count": 1,
                            "description": "",
                            "link": "http:\/\/localhost:8080\/tipo-prenda\/camisa\/",
                            "name": "Camisa",
                            "slug": "camisa",
                            "taxonomy": "tipo_prenda",
                            "meta": [],
                            "_links": {
                                "self": [
                                    {
                                        "href": "http:\/\/localhost:8080\/wp-json\/wp\/v2\/tipo_prenda\/6"
                                    }
                                ],
                                "collection": [
                                    {
                                        "href": "http:\/\/localhost:8080\/wp-json\/wp\/v2\/tipo_prenda"
                                    }
                                ],
                                "about": [
                                    {
                                        "href": "http:\/\/localhost:8080\/wp-json\/wp\/v2\/taxonomies\/tipo_prenda"
                                    }
                                ],
                                "wp:post_type": [
                                    {
                                        "href": "http:\/\/localhost:8080\/wp-json\/wp\/v2\/indicio?tipo_prenda=6"
                                    }
                                ],
                                "curies": [
                                    {
                                        "name": "wp",
                                        "href": "https:\/\/api.w.org\/{rel}",
                                        "templated": true
                                    }
                                ]
                            }
                        },
                        {
                            "id": 11,
                            "count": 1,
                            "description": "",
                            "link": "http:\/\/localhost:8080\/tipo-prenda\/chamarra\/",
                            "name": "Chamarra",
                            "slug": "chamarra",
                            "taxonomy": "tipo_prenda",
                            "meta": [],
                            "_links": {
                                "self": [
                                    {
                                        "href": "http:\/\/localhost:8080\/wp-json\/wp\/v2\/tipo_prenda\/11"
                                    }
                                ],
                                "collection": [
                                    {
                                        "href": "http:\/\/localhost:8080\/wp-json\/wp\/v2\/tipo_prenda"
                                    }
                                ],
                                "about": [
                                    {
                                        "href": "http:\/\/localhost:8080\/wp-json\/wp\/v2\/taxonomies\/tipo_prenda"
                                    }
                                ],
                                "wp:post_type": [
                                    {
                                        "href": "http:\/\/localhost:8080\/wp-json\/wp\/v2\/indicio?tipo_prenda=11"
                                    }
                                ],
                                "curies": [
                                    {
                                        "name": "wp",
                                        "href": "https:\/\/api.w.org\/{rel}",
                                        "templated": true
                                    }
                                ]
                            }
                        }
                    ]
                },
                "color": {
                    "info": {
                        "name": "Color",
                        "slug": "color",
                        "description": "",
                        "types": [
                            "indicio"
                        ],
                        "hierarchical": false,
                        "rest_base": "color",
                        "_links": {
                            "collection": [
                                {
                                    "href": "http:\/\/localhost:8080\/wp-json\/wp\/v2\/taxonomies"
                                }
                            ],
                            "wp:items": [
                                {
                                    "href": "http:\/\/localhost:8080\/wp-json\/wp\/v2\/color"
                                }
                            ],
                            "curies": [
                                {
                                    "name": "wp",
                                    "href": "https:\/\/api.w.org\/{rel}",
                                    "templated": true
                                }
                            ]
                        }
                    },
                    "terms": [
                        {
                            "id": 7,
                            "count": 1,
                            "description": "",
                            "link": "http:\/\/localhost:8080\/color\/verde\/",
                            "name": "Verde",
                            "slug": "verde",
                            "taxonomy": "color",
                            "meta": [],
                            "_links": {
                                "self": [
                                    {
                                        "href": "http:\/\/localhost:8080\/wp-json\/wp\/v2\/color\/7"
                                    }
                                ],
                                "collection": [
                                    {
                                        "href": "http:\/\/localhost:8080\/wp-json\/wp\/v2\/color"
                                    }
                                ],
                                "about": [
                                    {
                                        "href": "http:\/\/localhost:8080\/wp-json\/wp\/v2\/taxonomies\/color"
                                    }
                                ],
                                "wp:post_type": [
                                    {
                                        "href": "http:\/\/localhost:8080\/wp-json\/wp\/v2\/indicio?color=7"
                                    }
                                ],
                                "curies": [
                                    {
                                        "name": "wp",
                                        "href": "https:\/\/api.w.org\/{rel}",
                                        "templated": true
                                    }
                                ]
                            }
                        }
                    ]
                },
                "marca": {
                    "info": {
                        "name": "Marca",
                        "slug": "marca",
                        "description": "",
                        "types": [
                            "indicio"
                        ],
                        "hierarchical": false,
                        "rest_base": "marca",
                        "_links": {
                            "collection": [
                                {
                                    "href": "http:\/\/localhost:8080\/wp-json\/wp\/v2\/taxonomies"
                                }
                            ],
                            "wp:items": [
                                {
                                    "href": "http:\/\/localhost:8080\/wp-json\/wp\/v2\/marca"
                                }
                            ],
                            "curies": [
                                {
                                    "name": "wp",
                                    "href": "https:\/\/api.w.org\/{rel}",
                                    "templated": true
                                }
                            ]
                        }
                    },
                    "terms": [
                        {
                            "id": 8,
                            "count": 1,
                            "description": "",
                            "link": "http:\/\/localhost:8080\/marca\/cuidado-con-el-perro\/",
                            "name": "Cuidado con el perro",
                            "slug": "cuidado-con-el-perro",
                            "taxonomy": "marca",
                            "meta": [],
                            "_links": {
                                "self": [
                                    {
                                        "href": "http:\/\/localhost:8080\/wp-json\/wp\/v2\/marca\/8"
                                    }
                                ],
                                "collection": [
                                    {
                                        "href": "http:\/\/localhost:8080\/wp-json\/wp\/v2\/marca"
                                    }
                                ],
                                "about": [
                                    {
                                        "href": "http:\/\/localhost:8080\/wp-json\/wp\/v2\/taxonomies\/marca"
                                    }
                                ],
                                "wp:post_type": [
                                    {
                                        "href": "http:\/\/localhost:8080\/wp-json\/wp\/v2\/indicio?marca=8"
                                    }
                                ],
                                "curies": [
                                    {
                                        "name": "wp",
                                        "href": "https:\/\/api.w.org\/{rel}",
                                        "templated": true
                                    }
                                ]
                            }
                        }
                    ]
                },
                "talla": {
                    "info": {
                        "name": "Talla",
                        "slug": "talla",
                        "description": "",
                        "types": [
                            "indicio"
                        ],
                        "hierarchical": false,
                        "rest_base": "talla",
                        "_links": {
                            "collection": [
                                {
                                    "href": "http:\/\/localhost:8080\/wp-json\/wp\/v2\/taxonomies"
                                }
                            ],
                            "wp:items": [
                                {
                                    "href": "http:\/\/localhost:8080\/wp-json\/wp\/v2\/talla"
                                }
                            ],
                            "curies": [
                                {
                                    "name": "wp",
                                    "href": "https:\/\/api.w.org\/{rel}",
                                    "templated": true
                                }
                            ]
                        }
                    },
                    "terms": [
                        {
                            "id": 12,
                            "count": 1,
                            "description": "",
                            "link": "http:\/\/localhost:8080\/talla\/grande\/",
                            "name": "Grande",
                            "slug": "grande",
                            "taxonomy": "talla",
                            "meta": [],
                            "_links": {
                                "self": [
                                    {
                                        "href": "http:\/\/localhost:8080\/wp-json\/wp\/v2\/talla\/12"
                                    }
                                ],
                                "collection": [
                                    {
                                        "href": "http:\/\/localhost:8080\/wp-json\/wp\/v2\/talla"
                                    }
                                ],
                                "about": [
                                    {
                                        "href": "http:\/\/localhost:8080\/wp-json\/wp\/v2\/taxonomies\/talla"
                                    }
                                ],
                                "wp:post_type": [
                                    {
                                        "href": "http:\/\/localhost:8080\/wp-json\/wp\/v2\/indicio?talla=12"
                                    }
                                ],
                                "curies": [
                                    {
                                        "name": "wp",
                                        "href": "https:\/\/api.w.org\/{rel}",
                                        "templated": true
                                    }
                                ]
                            }
                        },
                        {
                            "id": 9,
                            "count": 1,
                            "description": "",
                            "link": "http:\/\/localhost:8080\/talla\/xl\/",
                            "name": "XL",
                            "slug": "xl",
                            "taxonomy": "talla",
                            "meta": [],
                            "_links": {
                                "self": [
                                    {
                                        "href": "http:\/\/localhost:8080\/wp-json\/wp\/v2\/talla\/9"
                                    }
                                ],
                                "collection": [
                                    {
                                        "href": "http:\/\/localhost:8080\/wp-json\/wp\/v2\/talla"
                                    }
                                ],
                                "about": [
                                    {
                                        "href": "http:\/\/localhost:8080\/wp-json\/wp\/v2\/taxonomies\/talla"
                                    }
                                ],
                                "wp:post_type": [
                                    {
                                        "href": "http:\/\/localhost:8080\/wp-json\/wp\/v2\/indicio?talla=9"
                                    }
                                ],
                                "curies": [
                                    {
                                        "name": "wp",
                                        "href": "https:\/\/api.w.org\/{rel}",
                                        "templated": true
                                    }
                                ]
                            }
                        }
                    ]
                },
                "material": {
                    "info": {
                        "name": "Material",
                        "slug": "material",
                        "description": "",
                        "types": [
                            "indicio"
                        ],
                        "hierarchical": false,
                        "rest_base": "material",
                        "_links": {
                            "collection": [
                                {
                                    "href": "http:\/\/localhost:8080\/wp-json\/wp\/v2\/taxonomies"
                                }
                            ],
                            "wp:items": [
                                {
                                    "href": "http:\/\/localhost:8080\/wp-json\/wp\/v2\/material"
                                }
                            ],
                            "curies": [
                                {
                                    "name": "wp",
                                    "href": "https:\/\/api.w.org\/{rel}",
                                    "templated": true
                                }
                            ]
                        }
                    },
                    "terms": [
                        {
                            "id": 10,
                            "count": 1,
                            "description": "",
                            "link": "http:\/\/localhost:8080\/material\/algodon\/",
                            "name": "Algodon",
                            "slug": "algodon",
                            "taxonomy": "material",
                            "meta": [],
                            "_links": {
                                "self": [
                                    {
                                        "href": "http:\/\/localhost:8080\/wp-json\/wp\/v2\/material\/10"
                                    }
                                ],
                                "collection": [
                                    {
                                        "href": "http:\/\/localhost:8080\/wp-json\/wp\/v2\/material"
                                    }
                                ],
                                "about": [
                                    {
                                        "href": "http:\/\/localhost:8080\/wp-json\/wp\/v2\/taxonomies\/material"
                                    }
                                ],
                                "wp:post_type": [
                                    {
                                        "href": "http:\/\/localhost:8080\/wp-json\/wp\/v2\/indicio?material=10"
                                    }
                                ],
                                "curies": [
                                    {
                                        "name": "wp",
                                        "href": "https:\/\/api.w.org\/{rel}",
                                        "templated": true
                                    }
                                ]
                            }
                        }
                    ]
                }
            },
            "posts": {
                "bitacora": {
                    "error": "HTTP 401 - Error fetching data"
                },
                "fosa": {
                    "error": "HTTP 401 - Error fetching data"
                },
                "indicio": {
                    "error": "HTTP 401 - Error fetching data"
                }
            },
            "media": []
        }
    }
]